Metadata-Version: 2.1
Name: kivy-history
Version: 1.0.3
Summary: kivy history inspired on javascript history api
Home-page: https://github.com/gmork2/kivy-history
Author: Fernando Morente
License: UNKNOWN
Keywords: kivy,history
Platform: UNKNOWN
Requires-Python: >=3
License-File: LICENSE
